turengcli/__init__.py
turengcli/__main__.py
turengcli/cli.py
turengcli-0.0.4.dist-info/METADATA
turengcli-0.0.4.dist-info/WHEEL
turengcli-0.0.4.dist-info/entry_points.txt
turengcli-0.0.4.dist-info/top_level.txt
turengcli-0.0.4.dist-info/RECORD
