Metadata-Version: 2.1
Name: turengcli
Version: 0.0.4
Summary: Command-line tool for tureng (tureng.com) with rich output.
Home-page: https://github.com/agmmnn/turengcli
Author: agmmnn
Classifier: Programming Language :: Python :: 3
Classifier: Operating System :: OS Independent
Classifier: Environment :: Console
Classifier: Topic :: Utilities
Requires-Python: >=3.7
Requires-Dist: requests
Requires-Dist: beautifulsoup4
Requires-Dist: rich
Requires-Dist: lxml
